discord_interactive/__init__.py
discord_interactive/help.py
discord_interactive/link.py
discord_interactive/page.py
discord_interactive-4.1.0.dist-info/LICENSE
discord_interactive-4.1.0.dist-info/METADATA
discord_interactive-4.1.0.dist-info/WHEEL
discord_interactive-4.1.0.dist-info/top_level.txt
discord_interactive-4.1.0.dist-info/RECORD
