Metadata-Version: 2.1
Name: discord-interactive
Version: 4.1.0
Summary: A package allowing you to display interactive help in Discord easily
Home-page: https://github.com/astariul/discord_interactive_help
Author: Nicolas REMOND
Author-email: remondnicola@gmail.com
License: MIT
Keywords: Discord,Interactive,Help
Platform: UNKNOWN
Classifier: License :: OSI Approved :: MIT License
Classifier: Programming Language :: Python :: 3.8
Classifier: Operating System :: OS Independent
Requires-Python: >=3.8
Requires-Dist: discord.py ~=2.3
Provides-Extra: all
Requires-Dist: pre-commit ~=3.0 ; extra == 'all'
Requires-Dist: black ~=23.1 ; extra == 'all'
Requires-Dist: ruff ~=0.0.272 ; extra == 'all'
Requires-Dist: mkdocs-material ~=9.0 ; extra == 'all'
Requires-Dist: mkdocstrings[python] ~=0.18 ; extra == 'all'
Requires-Dist: mike ~=1.1 ; extra == 'all'
Provides-Extra: dev
Requires-Dist: pre-commit ~=3.0 ; extra == 'dev'
Requires-Dist: black ~=23.1 ; extra == 'dev'
Requires-Dist: ruff ~=0.0.272 ; extra == 'dev'
Provides-Extra: docs
Requires-Dist: mkdocs-material ~=9.0 ; extra == 'docs'
Requires-Dist: mkdocstrings[python] ~=0.18 ; extra == 'docs'
Requires-Dist: mike ~=1.1 ; extra == 'docs'
Provides-Extra: hook
Requires-Dist: pre-commit ~=3.0 ; extra == 'hook'
Provides-Extra: lint
Requires-Dist: black ~=23.1 ; extra == 'lint'
Requires-Dist: ruff ~=0.0.272 ; extra == 'lint'
